bumbleview/__init__.py
bumbleview/bumblecore.py
bumbleview/main.py
bumbleview/plotting.py
bumbleview/data/.DS_Store
bumbleview/data/apis_sensoring.csv
bumbleview/data/background_green_leaf.csv
bumbleview/data/bombus_sensoring.csv
bumbleview/data/d65_standards.csv
bumbleview/data/eristalis_sensoring.csv
bumbleview/data/lucilia_sensoring.csv
bumbleview/data/macroglossum_sensoring.csv
bumbleview/data/musca_sensoring.csv
bumbleview/data/xmpl_data.csv
bumbleview/data/xmpl_meta.csv
bumbleview-0.2.8.dist-info/LICENSE
bumbleview-0.2.8.dist-info/METADATA
bumbleview-0.2.8.dist-info/WHEEL
bumbleview-0.2.8.dist-info/top_level.txt
bumbleview-0.2.8.dist-info/RECORD
