Metadata-Version: 2.1
Name: bumbleview
Version: 0.2.8
Summary: Convert physical spectra to excitation potential in insect eyes
Home-page: https://github.com/biothomme/Retinol.git
Author: thomas m huber
Author-email: thomas.huber@evobio.eu
License: MIT
Keywords: pollination,ecology,insect,vision,wavelength,color triangle,color hexagon,trichromatic,erg,electroretinogram
Platform: UNKNOWN
Requires-Dist: pandas
Requires-Dist: matplotlib
Requires-Dist: seaborn
Requires-Dist: scipy
Requires-Dist: statsmodels
